README.md
setup.cfg
setup.py
rasterbox/Image.py
rasterbox/Rasterbox.py
rasterbox/Target.py
rasterbox/__init__.py
rasterbox.egg-info/PKG-INFO
rasterbox.egg-info/SOURCES.txt
rasterbox.egg-info/dependency_links.txt
rasterbox.egg-info/requires.txt
rasterbox.egg-info/top_level.txt
rasterbox/utilities/DataManip.py
rasterbox/utilities/DataTest.py
rasterbox/utilities/Misc.py
rasterbox/utilities/__init__.py