Metadata-Version: 2.1
Name: rasterbox
Version: 0.0.2
Summary: Semantic access of raster images and target labels associated with rasters
Home-page: https://github.com/breadcrumbbuilds/rasterbox
Author: Brad Crump
Author-email: brad@breadcrumbbuilds.com
License: UNKNOWN
Keywords: RASTER,IMAGES,MACHINE,LEARNING
Platform: UNKNOWN
Classifier: Development Status :: 3 - Alpha
Classifier: Programming Language :: Python :: 3.6
Classifier: License :: OSI Approved :: MIT License
Classifier: Operating System :: OS Independent
Requires-Python: >=3.6
